{
    "name": "John Doe",
    "contact": {
        "email": "john.doe@example.com",
        "phone": "123-456-7890",
        "address": "123 Main St, Anytown, USA"
    },
    "summary": "Experienced software engineer with a strong background in developing scalable web applications and working with cross-functional teams.",
    "education": [
        {
            "institution": "University of Technology",
            "degree": "Bachelor of Science in Computer Science",
            "start_date": "September 2012",
            "end_date": "May 2016"
        }
    ],
    "experience": [
        {
            "company": "Tech Company",
            "position": "Senior Software Engineer",
            "start_date": "January 2020",
            "end_date": "Present",
            "responsibilities": [
                "Developed and maintained web applications using Python and JavaScript.",
                "Led a team of 5 engineers to deliver high-quality software on time.",
                "Collaborated with product managers and designers to define project requirements."
            ]
        },
        {
            "company": "Another Tech Company",
            "position": "Software Engineer",
            "start_date": "June 2016",
            "end_date": "December 2019",
            "responsibilities": [
                "Implemented new features and fixed bugs in a large-scale web application.",
                "Worked closely with QA team to ensure software quality.",
                "Participated in code reviews and provided feedback to peers."
            ]
        }
    ],
    "skills": {
        "programming_languages": [ "Python", "JavaScript", "SQL"],
        "frameworks": ["Django", "React"],
        "databases": ["PostgreSQL", "MySQL"],
        "web_technologies": ["HTML/CSS", "Django", "React"],
        "tools": ["Git", "Docker"],
        "other": ["Agile Development", "Scrum"]
    },
    "projects": [
        {
            "name": "Project Name",
            "description": "Brief description of the project and its purpose.",
            "technologies": ["Python", "Django", "JavaScript"]
        }
    ],
    "publications": [
        {
            "title": "Publication Title",
            "authors": ["John Doe", "Jane Smith"],
            "publication_date": "Month Year",
            "publisher": "Journal Name"
        }
    ],
    "certifications": [
        {
            "name": "Certification Name",
            "institution": "Issuing Organization",
            "date": "Month Year"
        }
    ]
    
}